{
	"id": 42116,
	"children": [
		{
			"id": 42123,
			"name": "culture of hip-hop -- as a uniting force"
		},
		{
			"id": 42117,
			"name": "culture of hip-hop -- entry into"
		},
		{
			"id": 42118,
			"name": "culture of hip-hop -- masculinist aspects"
		},
		{
			"id": 42119,
			"name": "culture of hip-hop -- mobile DJ scene"
		},
		{
			"id": 42120,
			"name": "culture of hip-hop -- non-African contributions"
		},
		{
			"id": 42121,
			"name": "culture of hip-hop -- racialization of"
		},
		{
			"id": 42122,
			"name": "culture of hip-hop -- significance to larger culture"
		},
		{
			"id": 42124,
			"name": "culture of hip-hop -- viewed as an Afro-diaspora form"
		}
	],
	"name": "hip-hop -- culture of"
}