{
	"id": 13503,
	"children": [
		{
			"id": 34924,
			"name": "Political psychology -- limits of"
		},
		{
			"id": 34925,
			"name": "Political psychology -- limits of focus on childhood and"
		},
		{
			"id": 34926,
			"name": "Political psychology -- linking psychological development to theories of"
		},
		{
			"id": 34927,
			"name": "Political psychology -- theories of, and Clinton presidency"
		},
		{
			"id": 34928,
			"name": "Political psychology -- traits theories and"
		}
	],
	"name": "Political -- psychology"
}