{
	"id": 29519,
	"children": [
		{
			"id": 29698,
			"name": "Darkness -- and filth"
		},
		{
			"id": 29759,
			"name": "Filth -- allure of"
		},
		{
			"id": 29716,
			"name": "Filth -- and disease"
		},
		{
			"id": 29765,
			"name": "Filth -- as smelly"
		},
		{
			"id": 29715,
			"name": "Filth -- criminals as (metaphor)"
		},
		{
			"id": 29760,
			"name": "Filth -- essential in punishment"
		},
		{
			"id": 29761,
			"name": "Filth -- gypsy view of"
		},
		{
			"id": 29762,
			"name": "Filth -- meanings of"
		},
		{
			"id": 29763,
			"name": "Filth -- metaphor of"
		},
		{
			"id": 29764,
			"name": "Filth -- relationship to wandering"
		},
		{
			"id": 29766,
			"name": "Filth -- wet as dirtier than dry"
		}
	],
	"name": "Filth"
}