{
	"id": 42847,
	"children": [
		{
			"id": 42856,
			"name": "free clinic movement -- and universal health care"
		},
		{
			"id": 42848,
			"name": "free clinic movement -- Barrio Free Clinic"
		},
		{
			"id": 42849,
			"name": "free clinic movement -- Black Panthers"
		},
		{
			"id": 42851,
			"name": "free clinic movement -- Fairfax"
		},
		{
			"id": 42852,
			"name": "free clinic movement -- Haight-Ashbury"
		},
		{
			"id": 42850,
			"name": "free clinic movement -- in California"
		},
		{
			"id": 42853,
			"name": "free clinic movement -- limits of"
		},
		{
			"id": 42854,
			"name": "free clinic movement -- Long Beach"
		},
		{
			"id": 42855,
			"name": "free clinic movement -- state repression, response"
		},
		{
			"id": 42857,
			"name": "free clinic movement -- Watts"
		}
	],
	"name": "free clinic movement"
}