{
	"id": 20955,
	"children": [
		{
			"id": 20956,
			"name": "Manufacturing -- agriculture and"
		},
		{
			"id": 27010,
			"name": "Manufacturing -- and African American employment"
		},
		{
			"id": 27011,
			"name": "Manufacturing -- and effect on wages of reduced reliance on human labor"
		},
		{
			"id": 20957,
			"name": "Manufacturing -- growth in"
		},
		{
			"id": 20958,
			"name": "Manufacturing -- problems in"
		},
		{
			"id": 20959,
			"name": "Manufacturing -- third-world"
		}
	],
	"name": "Manufacturing"
}