{
	"id": 7960,
	"children": [
		{
			"id": 7961,
			"name": "Stevenson, Robert Louis -- \"The Beach of Falesá\""
		},
		{
			"id": 30165,
			"name": "Stevenson, Robert Louis -- Kidnapped"
		},
		{
			"id": 29570,
			"name": "Stevenson, Robert Louis -- The Black Arrow"
		},
		{
			"id": 7962,
			"name": "Stevenson, Robert Louis -- The Dynamiter"
		},
		{
			"id": 7963,
			"name": "Stevenson, Robert Louis -- The New Arabian Nights"
		},
		{
			"id": 7964,
			"name": "Stevenson, Robert Louis -- The Strange Case of Dr. Jekyll and Mr. Hyde"
		},
		{
			"id": 30166,
			"name": "Stevenson, Robert Louis -- Treasure Island"
		}
	],
	"name": "Stevenson, Robert Louis"
}