{
	"id": 31361,
	"children": [
		{
			"id": 31363,
			"name": "Men -- African American"
		},
		{
			"id": 31362,
			"name": "Men -- and aggression"
		},
		{
			"id": 31371,
			"name": "Men -- and housework"
		},
		{
			"id": 31366,
			"name": "Men -- as breadwinners"
		},
		{
			"id": 31367,
			"name": "Men -- as caregivers"
		},
		{
			"id": 31384,
			"name": "Men -- as victims"
		},
		{
			"id": 31364,
			"name": "Men -- Asian"
		},
		{
			"id": 31365,
			"name": "Men -- backlash"
		},
		{
			"id": 31368,
			"name": "Men -- criminal liability"
		},
		{
			"id": 31206,
			"name": "Men -- custody of children"
		},
		{
			"id": 31369,
			"name": "Men -- experiences of"
		},
		{
			"id": 31370,
			"name": "Men -- false consciousness of"
		},
		{
			"id": 31372,
			"name": "Men -- images of, in legal decisions"
		},
		{
			"id": 31377,
			"name": "Men -- in nontraditional jobs"
		},
		{
			"id": 31378,
			"name": "Men -- in nurturing roles"
		},
		{
			"id": 31373,
			"name": "Men -- income"
		},
		{
			"id": 31374,
			"name": "Men -- Latino"
		},
		{
			"id": 31375,
			"name": "Men -- life expectancy"
		},
		{
			"id": 31376,
			"name": "Men -- Native American"
		},
		{
			"id": 31379,
			"name": "Men -- oppressions intertwined with women's"
		},
		{
			"id": 31380,
			"name": "Men -- prisoners"
		},
		{
			"id": 31381,
			"name": "Men -- reproductive rights"
		},
		{
			"id": 31382,
			"name": "Men -- societal expectations of, as solders"
		},
		{
			"id": 31383,
			"name": "Men -- suicide"
		}
	],
	"name": "Men"
}