{
	"id": 6912,
	"children": [
		{
			"id": 7415,
			"name": "V-Tech (Village Tech High) -- academic skills of students at"
		},
		{
			"id": 7433,
			"name": "V-Tech (Village Tech High) -- and TEACH Project"
		},
		{
			"id": 7420,
			"name": "V-Tech (Village Tech High) -- as continuation high school"
		},
		{
			"id": 7416,
			"name": "V-Tech (Village Tech High) -- attendance problems at"
		},
		{
			"id": 7417,
			"name": "V-Tech (Village Tech High) -- author's collaboration with"
		},
		{
			"id": 7418,
			"name": "V-Tech (Village Tech High) -- campus of"
		},
		{
			"id": 7419,
			"name": "V-Tech (Village Tech High) -- comprehensive high school and"
		},
		{
			"id": 7421,
			"name": "V-Tech (Village Tech High) -- demographic makeup of students at"
		},
		{
			"id": 7422,
			"name": "V-Tech (Village Tech High) -- discipline problems at"
		},
		{
			"id": 7423,
			"name": "V-Tech (Village Tech High) -- efforts to transform"
		},
		{
			"id": 7424,
			"name": "V-Tech (Village Tech High) -- Fractal Village research project at"
		},
		{
			"id": 7425,
			"name": "V-Tech (Village Tech High) -- motto of"
		},
		{
			"id": 7426,
			"name": "V-Tech (Village Tech High) -- name of"
		},
		{
			"id": 7427,
			"name": "V-Tech (Village Tech High) -- need for dynamic process of learning at"
		},
		{
			"id": 7428,
			"name": "V-Tech (Village Tech High) -- obstacles to learning at"
		},
		{
			"id": 7429,
			"children": [
				{
					"id": 7241,
					"name": "principal, V-Tech -- and professional development sessions"
				},
				{
					"id": 7240,
					"name": "principal, V-Tech -- background of"
				},
				{
					"id": 7242,
					"name": "principal, V-Tech -- relations with students"
				},
				{
					"id": 7243,
					"name": "principal, V-Tech -- support for teachers"
				},
				{
					"id": 7244,
					"name": "principal, V-Tech -- vision of"
				}
			],
			"name": "V-Tech (Village Tech High) -- principal at"
		},
		{
			"id": 7430,
			"name": "V-Tech (Village Tech High) -- sense of \"place\" at"
		},
		{
			"id": 7431,
			"name": "V-Tech (Village Tech High) -- students at"
		},
		{
			"id": 7432,
			"name": "V-Tech (Village Tech High) -- teachers at"
		},
		{
			"id": 7434,
			"name": "V-Tech (Village Tech High) -- theft at"
		}
	],
	"name": "V-Tech (Village Tech High)"
}