{
	"id": 946,
	"children": [
		{
			"id": 952,
			"name": "Tulane University -- and Gulfsouth Youth Action Camps"
		},
		{
			"id": 947,
			"name": "Tulane University -- Bring New Orleans Back Commission (BNOB)"
		},
		{
			"id": 948,
			"name": "Tulane University -- Center for Bioenvironmental Research"
		},
		{
			"id": 445,
			"name": "Tulane University -- Community Action Caucus of Tulane University Students (CACTUS)"
		},
		{
			"id": 949,
			"name": "Tulane University -- community service"
		},
		{
			"id": 950,
			"name": "Tulane University -- damage to facility"
		},
		{
			"id": 951,
			"name": "Tulane University -- English Department"
		},
		{
			"id": 953,
			"name": "Tulane University -- HOME, New Orleans"
		},
		{
			"id": 954,
			"name": "Tulane University -- Medical School"
		},
		{
			"id": 955,
			"name": "Tulane University -- Renewal Plan"
		},
		{
			"id": 956,
			"name": "Tulane University -- Shakespeare Festival"
		}
	],
	"name": "Tulane University"
}