{
	"id": 30405,
	"children": [
		{
			"id": 30407,
			"name": "conspiracy, argument from -- American Revolution compared to abolitionism"
		},
		{
			"id": 30406,
			"name": "conspiracy, argument from -- in American Revolution"
		},
		{
			"id": 30411,
			"name": "conspiracy, argument from -- in Welch's rhetoric"
		},
		{
			"id": 30409,
			"name": "conspiracy, argument from -- McCarthys use of"
		},
		{
			"id": 30410,
			"name": "conspiracy, argument from -- slave power"
		},
		{
			"id": 30408,
			"name": "conspiracy, argument from -- used against gay liberation"
		}
	],
	"name": "conspiracy, argument from"
}