{
	"id": 12056,
	"children": [
		{
			"id": 21328,
			"name": "Bleak House (Dickens) -- as fantasy of reparation"
		},
		{
			"id": 21325,
			"name": "Bleak House (Dickens) -- dead baby and psychic inheritance in"
		},
		{
			"id": 21326,
			"name": "Bleak House (Dickens) -- existential center of"
		},
		{
			"id": 21327,
			"name": "Bleak House (Dickens) -- falsifying institutions in"
		},
		{
			"id": 21329,
			"name": "Bleak House (Dickens) -- father-daughter relationship in"
		},
		{
			"id": 21330,
			"name": "Bleak House (Dickens) -- illegitimacy in sense of sin and shame in"
		},
		{
			"id": 21331,
			"name": "Bleak House (Dickens) -- inconsistencies in plot of"
		},
		{
			"id": 21332,
			"name": "Bleak House (Dickens) -- moral of"
		},
		{
			"id": 21333,
			"name": "Bleak House (Dickens) -- orphan theme in"
		}
	],
	"name": "Dickens, Charles -- Bleak House"
}