{
	"id": 13819,
	"children": [
		{
			"id": 16764,
			"name": "Sense of self -- and \"mirroring\""
		},
		{
			"id": 16760,
			"name": "Sense of self -- dread of loss of self"
		},
		{
			"id": 16761,
			"name": "Sense of self -- healthy social self"
		},
		{
			"id": 16762,
			"name": "Sense of self -- inner self"
		},
		{
			"id": 16763,
			"name": "Sense of self -- mental and emotional equilibrium"
		},
		{
			"id": 16765,
			"name": "Sense of self -- self-division"
		},
		{
			"id": 16767,
			"name": "Sense of self -- sense of individuality and separateness"
		},
		{
			"id": 16766,
			"name": "Sense of self -- sense of reality, cohesion, and identity"
		},
		{
			"id": 16768,
			"name": "Sense of self -- solipsistic state of mind"
		},
		{
			"id": 16769,
			"name": "Sense of self -- threat of annihilation"
		}
	],
	"name": "Self -- sense of"
}