{
	"id": 45171,
	"children": [
		{
			"id": 45173,
			"name": "Park Chung Hee regime -- authoritarianism of"
		},
		{
			"id": 45174,
			"name": "Park Chung Hee regime -- coup"
		},
		{
			"id": 45175,
			"name": "Park Chung Hee regime -- developmentalist projects"
		},
		{
			"id": 45176,
			"name": "Park Chung Hee regime -- discourses of"
		},
		{
			"id": 45177,
			"name": "Park Chung Hee regime -- early stages"
		},
		{
			"id": 45178,
			"name": "Park Chung Hee regime -- Evergreen approved by"
		},
		{
			"id": 45179,
			"name": "Park Chung Hee regime -- filmmaking as focal point"
		},
		{
			"id": 45180,
			"name": "Park Chung Hee regime -- ideology"
		},
		{
			"id": 45181,
			"name": "Park Chung Hee regime -- industrialization"
		},
		{
			"id": 45182,
			"name": "Park Chung Hee regime -- Shin's relations with"
		}
	],
	"name": "Park Chung Hee regime"
}