{
	"id": 12895,
	"children": [
		{
			"id": 12896,
			"name": "Decisions/decision making -- acceptability"
		},
		{
			"id": 12897,
			"name": "Decisions/decision making -- advice"
		},
		{
			"id": 12898,
			"name": "Decisions/decision making -- centrality of in modern life"
		},
		{
			"id": 12900,
			"name": "Decisions/decision making -- cognitive and emotional flexibility in"
		},
		{
			"id": 12901,
			"name": "Decisions/decision making -- consensus building"
		},
		{
			"id": 12902,
			"name": "Decisions/decision making -- consultation with others in"
		},
		{
			"id": 12903,
			"name": "Decisions/decision making -- policy"
		},
		{
			"id": 12904,
			"name": "Decisions/decision making -- political"
		},
		{
			"id": 12905,
			"name": "Decisions/decision making -- processes"
		},
		{
			"id": 12906,
			"name": "Decisions/decision making -- quality"
		},
		{
			"id": 12907,
			"name": "Decisions/decision making -- routines"
		},
		{
			"id": 12908,
			"name": "Decisions/decision making -- rules"
		},
		{
			"id": 12909,
			"name": "Decisions/decision making -- style"
		},
		{
			"id": 12899,
			"name": "Decisions/decision making -- William J. Clinton's"
		}
	],
	"name": "Decisions/decision making"
}